neuronix/Decision_Tree.py
neuronix/Decision_Tree_Reg.py
neuronix/KNN.py
neuronix/Random_forest.py
neuronix/SVM.py
neuronix/XGBoost.py
neuronix/__init__.py
neuronix/linear_regression.py
neuronix/logistic_regression.py
neuronix/multiple_regression.py
neuronix-0.1.0.dist-info/LICENSE
neuronix-0.1.0.dist-info/METADATA
neuronix-0.1.0.dist-info/WHEEL
neuronix-0.1.0.dist-info/top_level.txt
neuronix-0.1.0.dist-info/RECORD
