Metadata-Version: 2.2
Name: neuronix
Version: 0.1.0
Summary: A Collection of Machine Learning Algorithms implemented from Scratch
Home-page: https://github.com/username/neuron
Author: Karthikeyan
Author-email: Karthikeyan <karthikkrishna0907@gmail.com>
License: MIT License
Project-URL: Homepage, https://github.com
Project-URL: Issues, https://github.com
Classifier: Programming Language :: Python :: 3
Classifier: Operating System :: OS Independent
Requires-Python: >=3.6
License-File: LICENSE
Dynamic: author
Dynamic: home-page
Dynamic: requires-python
